README.md
setup.py
tornado_stale_client/__init__.py
tornado_stale_client/client.py
tornado_stale_client.egg-info/PKG-INFO
tornado_stale_client.egg-info/SOURCES.txt
tornado_stale_client.egg-info/dependency_links.txt
tornado_stale_client.egg-info/requires.txt
tornado_stale_client.egg-info/top_level.txt