Metadata-Version: 1.1
Name: tornado-stale-client
Version: 0.2.1
Summary: An async http client for tornado with stale cache support
Home-page: https://github.com/globocom/tornado-stale-client
Author: Globo.com
Author-email: backstage@corp.globo.com
License: MIT
Keywords: tornado async http client redis stale cache
Platform: UNKNOWN
Classifier: Development Status :: 4 - Beta
Classifier: Intended Audience :: Developers
Classifier: License :: OSI Approved :: MIT License
Classifier: Natural Language :: English
Classifier: Operating System :: Unix
Classifier: Programming Language :: Python :: 3.4
Classifier: Operating System :: OS Independent
